pymapper/__init__.py
pymapper/mapper.py
py_mapper-1.0.0a0.dist-info/LICENSE
py_mapper-1.0.0a0.dist-info/METADATA
py_mapper-1.0.0a0.dist-info/WHEEL
py_mapper-1.0.0a0.dist-info/top_level.txt
py_mapper-1.0.0a0.dist-info/RECORD
