Metadata-Version: 2.1
Name: py-mapper
Version: 1.0.0a0
Summary: Python mapper library
Home-page: https://github.com/endlichfelipe/py-mapper
Author: Felipe Endlich
Author-email: endlichfelipe@gmail.com
License: MIT
Keywords: MAPPER
Platform: UNKNOWN
Classifier: Development Status :: 3 - Alpha
Classifier: Intended Audience :: Developers
Classifier: Topic :: Software Development :: Libraries
Classifier: Operating System :: OS Independent
Classifier: License :: OSI Approved :: MIT License
Classifier: Programming Language :: Python :: 3
Requires-Python: >=3.6
License-File: LICENSE
